{
  "zip_target_map": {
    "75001": 9.247775874531602,
    "75006": 8.209634384825176,
    "75007": 8.309679804541622,
    "75019": 12.275278745179063,
    "75039": 9.007876387955562,
    "75041": 9.49931719477567,
    "75042": 8.621340357804442,
    "75050": 7.7182279339278095,
    "75051": 10.625730910380858,
    "75052": 5.991464547107982,
    "75062": 11.814584380339777,
    "75080": 9.490517747049397,
    "75081": 10.094707826106184,
    "75089": 9.30150115037316,
    "75104": 8.396726490392142,
    "75115": 10.110923956151167,
    "75116": 7.600902459542082,
    "75134": 12.154873393478534,
    "75141": 8.390949464841986,
    "75149": 10.186718530348319,
    "75150": 8.695837951531756,
    "75159": 11.300225525286555,
    "75180": 9.555598916341333,
    "75201": 10.52711961971375,
    "75202": 10.264878458294854,
    "75203": 8.887295289985179,
    "75204": 9.688225564882917,
    "75205": 10.060167875734441,
    "75206": 9.317641718708952,
    "75207": 9.48163173885454,
    "75208": 8.995191522294089,
    "75209": 8.929993620950611,
    "75210": 6.82345919351452,
    "75211": 8.699906802700857,
    "75212": 9.187498001822158,
    "75214": 8.876171128193539,
    "75215": 8.624860658300287,
    "75216": 8.46277954747892,
    "75217": 8.500149526356465,
    "75218": 8.772687944475168,
    "75219": 9.831887373466808,
    "75220": 8.141931351703603,
    "75223": 8.40231932348314,
    "75224": 8.326476806632153,
    "75225": 9.348481090445027,
    "75226": 10.692757625527292,
    "75227": 8.47671435169727,
    "75228": 8.48759841649574,
    "75229": 8.723704992945672,
    "75230": 9.034786600790495,
    "75231": 8.71024097214164,
    "75232": 8.483848448212862,
    "75233": 8.550445925764478,
    "75234": 8.865951660281153,
    "75235": 9.297268494371849,
    "75236": 9.417302202160277,
    "75237": 9.395666316020788,
    "75238": 8.829869627567545,
    "75240": 9.237587249624173,
    "75241": 8.668201443283436,
    "75243": 8.58250537678218,
    "75244": 9.048170457935644,
    "75246": 9.297167887843786,
    "75247": 9.499895719149613,
    "75248": 8.627583597869993,
    "75249": 8.347149367179405,
    "75251": 10.287486128557472,
    "75252": 9.782435367867953,
    "75253": 8.217432543019656,
    "75254": 8.573279237500234
  },
  "zip_overall_mean": 8.887894601617479,
  "land_use_freq_map": {
    "SINGLE FAMILY DWELLING": 77641,
    "MULTI-FAMILY DWELLING": 10394,
    "OFFICE BUILDING": 6330,
    "VACANT FLOOR SPACE": 3211,
    "RESTAURANT WITHOUT DRIVE-IN SERVICE": 2551,
    "GEN MERCHANDISE OR FOOD STORE < 3500 SQ. FT.": 2230,
    "OFFICE SHOWROOM/WAREHOUSE": 2061,
    "GEN MERCHANDISE OR FOOD STORE > 3500 SQ. FT.": 1683,
    "COMMUNICATIONS": 1592,
    "FAIRGROUNDS": 1396,
    "TWO FAMILY DWELLING": 1330,
    "STREET BARRICADE": 1156,
    "PERSONAL SERVICE USE": 1088,
    "MEDICAL CLINIC OR AMBULATORY SURGICAL CENTER": 946,
    "RESTAURANT WITH DRIVE-IN SERVICE": 917,
    "TOWER/ANTENNA FOR CELLULAR COMMUNICATION": 907,
    "HOTEL": 860,
    "PUBLIC OR PRIVATE SCHOOL": 790,
    "CHURCH, SYNAGOGUE, TEMPLE, MOSQUE": 640,
    "SHELL BUILDING": 584,
    "WAREHOUSE": 445,
    "HOSPITAL": 434,
    "VEHICLE DISPLAY,SALES AND SERVICE": 368,
    "COMMERCIAL AMUSEMENT (INSIDE)": 332,
    "INDUSTRIAL (INSIDE)": 312,
    "MANUFACTURED HOME PARK": 293,
    "PUBLIC PARK, PLAYGROUND, OR GOLF COURSE": 262,
    "FINANCIAL INSTITUTION WITH DRIVE-IN WINDOW": 252,
    "AUTO SERVICE CENTER": 250,
    "UTILITIES": 242,
    "COMMERCIAL PARKING LOT OR GARAGE": 220,
    "RETIREMENT HOUSING": 218,
    "MINI-WAREHOUSE": 197,
    "FINANCIAL INSTITUTION WITHOUT DRIVE-IN WINDOW": 181,
    "VEHICLE OR ENGINE REPAIR OR MAINTENANCE": 173,
    "SIDEWALK BARRICADE": 171,
    "COLLEGE, UNIVERSITY, OR SEMINARY": 156,
    "ALCOHOLIC BEVERAGE ESTABLISHMENT": 152,
    "COMMERCIAL": 150,
    "UNDEVELOPED LAND AREA": 144,
    "INDUSTRIAL (INSIDE) FOR LIGHT MANUFACTURING": 143,
    "CHILD CARE FACILITY": 127,
    "MACHINERY, HEAVY EQUIP. OR TRUCK SALES & SERVICE": 121,
    "ANIMAL SHELTER OR CLINIC": 117,
    "CONVALESCENT & NURSING HOMES & RELATED INSTITUTION": 113,
    "PRIVATE RECREATION CENTER, CLUB OR AREA": 112,
    "DRY CLEANING OR LAUNDRY STORE": 102,
    "UTILITY OR GOVERNMENTAL INSTALLATION (OTHER)": 99,
    "CAR WASH": 93,
    "AIRPORT OR LANDING FIELD": 88,
    "MIXED INCOME MULTI-FAMILY": 85,
    "Motor Vehicle Fueling Station": 85,
    "FURNITURE STORE": 84,
    "LIQUOR STORE": 75,
    "COMMUNITY SERVICE CENTER": 73,
    "GEN MERCHANDISE (NO FOOD) STORE < 3500 SQ. FT": 72,
    "COMMON GREEN": 69,
    "SHOPPING CENTER": 67,
    "COUNTRY CLUB WITH PRIVATE MEMBERSHIP": 66,
    "HOME IMPROVEMENT CENTER/ BLDG MATERIALS SALES YARD": 66,
    "THEATER": 64,
    "COMMERCIAL AMUSEMENT (OUTSIDE)": 60,
    "FIRE STATION": 54,
    "LOCAL UTILITIES": 50,
    "DETACHED NON-PREMISE SIGN": 46,
    "MEDICAL OR SCIENTIFIC LABORATORY": 45,
    "CATERING SERVICE": 43,
    "TEMPORARY CONSTRUCTION OFFICE": 42,
    "PAWN SHOP": 41,
    "MUSEUM": 41,
    "GEN MERCHANDISE OR FOOD STORE>=100000 SQ FT": 40,
    "SURFACE PARKING": 38,
    "MORTUARY, FUNERAL HOME, OR COMM. WEDDING CHAPEL": 38,
    "FREIGHT TERMINAL": 37,
    "JOB OR LITHOGRAPHIC PRINTING": 32,
    "COMMERCIAL BUS STATION AND TERMINAL": 31,
    "OUTSIDE STORAGE": 31,
    "Truck Stop": 29,
    "INDUSTRIAL (INSIDE) POTENTIALLY INCOMPATIBLE": 28,
    "OTHER TRNSP,CONMUN & UTILITIES": 28,
    "PRIMARY SCHOOL": 28,
    "MOTEL": 28,
    "BUSINESS SCHOOL": 27,
    "TECHNICAL SCHOOL": 26,
    "TRADE CENTER": 26,
    "TRANSIT PASSENGER STATION OR TRANSFER CENTER": 26,
    "FITNESS CENTER": 24,
    "CUSTOM BUSINESS SERVICES": 24,
    "OUTDOOR ADVERTISING": 20,
    "INDUSTRIAL (OUTSIDE)": 20,
    "LIBRARY": 19,
    "MACHINE OR WELDING SHOP": 17,
    "NURSERY, GARDEN SHOP, OR PLANT SALES": 17,
    "DEPARTMENT STORES-RETAIL": 17,
    "CROP PRODUCTION": 16,
    "ART GALLERY": 16,
    "CONTRACTOR'S MAINTENANCE YARD": 16,
    "MISCELLANEOUS": 16,
    "ELECTRONICS SERVICE CENTER": 15,
    "Alcoholic beverage manufacturing": 15,
    "SECONDARY SCHOOL": 15,
    "CUSTOM WOODWORKING, FURNITURE CONSTRUCTION OR REP": 15,
    "GROCERIES-RETAIL": 15,
    "GROUP HOME OR SHELTER": 15,
    "TEMPORARY CONCRETE OR ASPHALT BATCHING PLANT": 14,
    "BANK RELATED FUNCTIONS": 14,
    "ADULT DAY CARE FACILITY": 14,
    "MUNICIPAL SERVICE CENTER": 14,
    "NURSERY SCHOOL": 13,
    "HANDICAPPED GROUP DWELLING": 13,
    "METAL SALVAGE FACILITY": 13,
    "FOSTER HOME": 13,
    "TEMPORARY RETAIL USE (INCLUDES CHRISTMAS TREE LOT)": 13,
    "COMMERCIAL MOTOR VEHICLE PARKING": 12,
    "CEMETERY OR MAUSOLEUM": 12,
    "COMMERCIAL CLEANING OR LAUNDRY PLANT": 12,
    "BUILDING REPAIR & MAINTENANCE SHOP": 12,
    "FOOD OR BEVERAGE STORE  <= 3,500 SQ. FT.": 11,
    "POLICE STATION": 11,
    "COLLEGE DORMITORY": 10,
    "TOOL OR EQUIPMENT RENTAL": 10,
    "PERSONAL SERVICES": 10,
    "PETROLEUM PRODUCT STORAGE AND WHOLESALE": 9,
    "BUS OR RAIL TRANSIT VEHICLE MAINTANCE OR STORAGE": 9,
    "AUTO AUCTION": 9,
    "GROUP RESIDENTIAL FACILITY": 9,
    "PARAPHERNALIA SHOP": 8,
    "WATER TREATMENT PLANT": 8,
    "DENTIST": 7,
    "AMUSEMENT": 7,
    "RESIDENTIAL HOTEL": 7,
    "PROFESSIONAL SCHOOL": 7,
    "BANKING SERVICES": 7,
    "OVERNIGHT GENERAL PURPOSE SHELTER": 6,
    "TRANSIT PASSENGER SHELTER": 6,
    "JUNIOR COLLEGE": 5,
    "CONVENT OR MONASTERY": 5,
    "OTHER AUTO SERVICES": 5,
    "PRIVATE STABLE": 4,
    "FLOOD CONTROL PUMP STATION": 4,
    "COMMERCIAL RADIO TRANSMITTING STATION": 4,
    "MTR VEH USED CAR ONLY RETAIL--CODE NO LONGER USED": 4,
    "RAILROAD YARD, ROUNDHOUSE, OR SHOPS": 3,
    "SANITARY LANDFILL": 3,
    "PETROLEUM REFIN & RELATED PR": 3,
    "VEHICLE STORAGE LOT": 3,
    "PUBLIC ASSEMBLY": 3,
    "POST OFFICE": 3,
    "RADIO, TELEVISION OR MICROWAVE TOWER": 3,
    "ACCESSORY BUILDING TO SINGLE FAMILY DWELLING": 3,
    "TEMP SALES OFFICE - REAL ESTATE": 3,
    "PRIVATE STREET OR ALLEY": 2,
    "MISC MANUFACTURING, NEC": 2,
    "GOVERNMENTAL SERVICES": 2,
    "LODGING OR BOARDING HOUSE": 2,
    "RESIDENTIAL GARAGE OR CARPORT": 2,
    "INDUSTRIAL (OUTSIDE) POTENTIALLY INCOMPATIBLE": 2,
    "RAILROAD PASSENGER STATION": 2,
    "ADVERTISING SERVICES GENERAL": 2,
    "REFUSE TRANSFER STATION": 2,
    "TEMPORARY TENT - RETAIL": 2,
    "HALFWAY HOUSE": 2,
    "HOUSEHOLD EQUIPMENT & APPLIANCE REPAIR": 2,
    "OUTSIDE SALVAGE & RECLAMATION": 2,
    "REPAIR SERVICES": 2,
    "OTHER ADVERTIS SERV, NEC": 1,
    "AMBULANCE SERVICE": 1,
    "INSTITUTE FOR SPECIAL EDUCATION": 1,
    "ELECTRICAL SUBSTATION": 1,
    "SAND, GRAVEL, OR EARTH SALES AND STORAGE": 1,
    "CONV FROM 2 FAMILY TO SFD": 1,
    "MUNICIPAL WASTE INCINERATOR": 1,
    "JUNIOR HIGH SCHOOL": 1,
    "HELIPORT": 1,
    "STREET DECORATIONS": 1,
    "Special Institutional Uses": 1,
    "SPECIAL PURPOSE SIGN": 1,
    "COMMERCIAL TELEVISION TRANSMITTING STATION": 1,
    "FARM": 1,
    "COMMERCIAL STABLE": 1,
    "HAZARDOUS WASTE MANAGEMENT FACILITY": 1,
    "Accessory Community Center (Private)": 1,
    "Alternative Financial Institutions": 1,
    "RECYCLING COLLECTION CENTER": 1,
    "SAVINGS & LOAN ASSOCIATION": 1,
    "PARK PUBLIC ROW": 1,
    "SEWAGE TREATMENT PLANT": 1,
    "ANIMAL PRODUCTION": 1,
    "MOTOR VEHICLE TRANSPORTATION": 1
  },
  "permit_code_freq_map": {
    "BU": 44735,
    "PL": 25360,
    "EL": 15616,
    "ME": 12140,
    "LS": 3893,
    "FE": 3422,
    "EW": 2811,
    "SW": 1810,
    "PV": 1521,
    "SE": 1388,
    "BA": 1331,
    "FA": 1222,
    "LL": 515,
    "FI": 218,
    "TE": 139,
    "EX": 96,
    "GP": 67,
    "FS": 59,
    "TR": 58,
    "MR": 38,
    "BF": 17,
    "FL": 16,
    "MG": 2,
    "CS": 1,
    "EV": 1
  },
  "city_freq_map": {
    "DALLAS": 36482,
    "Unknown": 12946,
    "MESQUITE": 6577,
    "GARLAND": 6085,
    "IRVING": 5804,
    "PLANO": 4490,
    "FORT WORTH": 4147,
    "CARROLLTON": 3281,
    "RICHARDSON": 2853,
    "ARLINGTON": 2812,
    "LEWISVILLE": 2773,
    "GRAND PRAIRIE": 1679,
    "FARMERS BRANCH": 1592,
    "FRISCO": 1584,
    "GRAPEVINE": 1436,
    "ROCKWALL": 1435,
    "MCKINNEY": 1397,
    "ROWLETT": 1257,
    "FORNEY": 1133,
    "ADDISON": 973,
    "FT WORTH": 932,
    "DUNCANVILLE": 822,
    "EULESS": 748,
    "DESOTO": 747,
    "WYLIE": 624,
    "ALLEN": 617,
    "CEDAR HILL": 599,
    "DENTON": 572,
    "KAUFMAN": 558,
    "TERRELL": 520,
    "AUSTIN": 510,
    "RED OAK": 495,
    "CROWLEY": 479,
    "HOUSTON": 477,
    "THE COLONY": 463,
    "HALTOM CITY": 455,
    "SUNNYVALE": 439,
    "FATE": 432,
    "MIDLOTHIAN": 430,
    "MANSFIELD": 429,
    "COPPELL": 421,
    "WAXAHACHIE": 403,
    "SEAGOVILLE": 397,
    "SOUTHLAKE": 381,
    "LANCASTER": 356,
    "FLOWER MOUND": 355,
    "HEATH": 350,
    "KENNEDALE": 317,
    "THE WOODLANDS": 290,
    "HURST": 286,
    "KELLER": 284,
    "BURLESON": 272,
    "BALCH SPRINGS": 245,
    "SACHSE": 240,
    "RICHLAND HILLS": 235,
    "ROYCE CITY": 233,
    "GAINSEVILLE": 228,
    "ROYSE CITY": 214,
    "GRAND PRARIE": 208,
    "QUINLAN": 206,
    "FARMERSBRANCH": 189,
    "NORTH RICHLAND HILLS": 179,
    "FARMERSVILLE": 176,
    "ENNIS": 174,
    "FARMARS BRANCH": 170,
    "BEDFORD": 165,
    "GRANDPRAIRE": 156,
    "PROSPER": 155,
    "WEATHERFORD": 151,
    "LITTLE ELM": 149,
    "GRAND PRAIRE": 134,
    "SAN ANTONIO": 134,
    "FERRIS": 126,
    "CORSICANA": 125,
    "LAVON": 122,
    "ALEDO": 121,
    "COLLEYVILLE": 119,
    "CRANDALL": 111,
    "CELINA": 109,
    "AUBREY": 108,
    "POINT": 106,
    "CANTON": 102,
    "CYPRESS": 98,
    "HASLET": 92,
    "PALMER": 91,
    "TYLER": 91,
    "NEVADA": 91,
    "LAKE DALLAS": 89,
    "ALVARADO": 89,
    "CROSSROADS": 87,
    "CLEBURNE": 83,
    "ANNA": 82,
    "HUTCHINS": 81,
    "OVILLA": 81,
    "KEMP": 80,
    "TROPHY CLUB": 74,
    "GUN BARREL": 73,
    "NEW  BRAUNFELS": 73,
    "SACHE": 73,
    "MELISSA": 71,
    "WACO": 71,
    "SAGINAW": 70,
    "ROANOKE": 54,
    "ADDISION": 53,
    "PARIS": 53,
    "AZLE": 53,
    "CADDO MILLS": 51,
    "HALTOM": 50,
    "PANTEGO": 49,
    "GLENN HEIGHTS": 49,
    "GEORGETOWN": 47,
    "FOREST HILL": 46,
    "WILLS POINT": 45,
    "COMBINE": 45,
    "GALVESTON": 45,
    "LEANARD": 45,
    "SOUTH LAKE": 44,
    "MURPHY": 43,
    "MABANK": 43,
    "GRANDBURY": 42,
    "GUNTER": 42,
    "WILMER": 42,
    "CONROE": 42,
    "MARTINDALE": 42,
    "WHITE SETTLEMENT": 41,
    "PONDER": 41,
    "LUCAS": 41,
    "PRINCETON": 41,
    "OAK POINT": 40,
    "CORINTH": 40,
    "GARLAND PRAIRIE": 40,
    "EUSTACE": 39,
    "GREENVILLE": 39,
    "SCURRY": 38,
    "VAN ALSTYNE": 38,
    "YANTIS": 37,
    "CARROLTON": 37,
    "DALWORTHINGTON GARDENS": 37,
    "DICKINSON": 37,
    "FT  WORTH": 36,
    "COPEVILLE": 36,
    "SANGER": 35,
    "KATY": 35,
    "BENBROOK": 34,
    "RICHARSON": 32,
    "JUSTIN": 30,
    "GRANBURY": 30,
    "UNIVERSITY PARK": 30,
    "SUNYVALE": 29,
    "ARGYLE": 29,
    "HEALTH": 29,
    "MAYPEARL": 29,
    "LAKE KIOWA": 29,
    "HIGHLAND VILLAGE": 26,
    "FAIRVIEW": 26,
    "FORTH WORTH": 26,
    "HUNTSVILLE": 26,
    "FARMES BRANCH": 26,
    "SPRINGTOWN": 25,
    "DALAS": 25,
    "WATAUGA": 24,
    "VENUS": 24,
    "SHERMAN": 24,
    "HUMBLE": 24,
    "HONEY GROVE": 24,
    "GUN BARRELL CITY": 23,
    "TOMBALL": 22,
    "HEARTLAND": 21,
    "ROYSCE CITY": 21,
    "DECATUR": 20,
    "ROYSE": 20,
    "ROUND ROCK": 19,
    "VALLEY VIEW": 19,
    "GRANDVIEW": 19,
    "SELMA": 19,
    "BOYD": 19,
    "KRUM": 19,
    "SPRING": 18,
    "LONGVIEW": 18,
    "CARRROLLTON": 18,
    "STAFFORD": 17,
    "HICKORY CREEK": 17,
    "WAXACHIE": 17,
    "NEW BRAUUNFELS": 17,
    "WHITESBORO": 16,
    "BOWIE": 16,
    "NORTHLAKE": 16,
    "PFLUGERVILLE": 16,
    "GODLEY": 16,
    "WILLIS POINT": 15,
    "MOLAKOFF": 14,
    "DALLS": 14,
    "DONNA": 14,
    "BELTON": 13,
    "WHITEWRIGHT": 13,
    "POTTSBORO": 13,
    "RIVER OAKS": 13,
    "FARMER BRANCH": 12,
    "GAND PRAIRIE": 12,
    "EDGEWOOD": 12,
    "JOSHUA": 12,
    "GLEN HEIGHTS": 12,
    "TEXARKANA": 12,
    "ROYCE": 12,
    "DFW AIRPORT": 12,
    "RICHARDON": 11,
    "ARLINGTION": 11,
    "WICHITA FALLS": 11,
    "PILOT POINT": 11,
    "WILLIS": 11,
    "HILLSBORO": 11,
    "SULPHUR SPRINGS": 11,
    "GLADEWATER": 10,
    "LEWSIVILLE": 10,
    "RICE": 10,
    "SEHRMAN": 10,
    "N RICHLAND HILLS": 10,
    "PLANOT": 10,
    "WHEATHERFORD": 10,
    "CAMERON": 10,
    "GAINESVILLE": 9,
    "DALWORTHINGTON GARD": 9,
    "GRANDPRAIRIE": 9,
    "NEWARK": 9,
    "WOLFE CITY": 9,
    "GORDONVILLE": 9,
    "KRUGERVILLE": 9,
    "ARYGLE": 9,
    "LEONARD": 8,
    "N RICHLAND HILL": 8,
    "DALALS": 8,
    "RHOME": 8,
    "SUNSET": 8,
    "EVERMAN": 8,
    "HACHBERRY": 8,
    "BARRY": 8,
    "MINEOLA": 8,
    "TRENTON": 8,
    "LANTANA": 8,
    "MUPRHY": 8,
    "DENISON": 7,
    "NORTH RICHLAND HILLSQ": 7,
    "ROWLET": 7,
    "OAK LEAF": 7,
    "ITALY": 7,
    "TENNESSEE COLONY": 7,
    "SALTILLO": 7,
    "PARKER": 7,
    "JOSEPHINE": 7,
    "ROCKWELL": 7,
    "GUN BARREL CITY": 7,
    "BARTONVILLE": 7,
    "GRAND SALINE": 7,
    "MCQUEENEY": 7,
    "LUBBOCK": 7,
    "BEN WHEELER": 7,
    "FRIENDS WOOD": 7,
    "TOLAR": 7,
    "ARP": 7,
    "JONESTOWN": 7,
    "BONHAM": 6,
    "BLUE RIDGE": 6,
    "LILLIAN": 6,
    "BLUERIDGE": 6,
    "MIDOLOTHIAN": 6,
    "WEBSTER": 6,
    "HOWE": 6,
    "ATHENS": 6,
    "CEDAR PARK": 6,
    "FLOUND MOUND": 6,
    "KINGWOOD": 6,
    "SEGUIN": 6,
    "BULVERDE": 6,
    "WHITESETTLEMENT": 6,
    "ROCKWALL TX": 6,
    "MANSFILED": 5,
    "DOUBLE OAK": 5,
    "AVERY": 5,
    "NEW WAVERLY": 5,
    "WILLOW PARK": 5,
    "MERIT": 5,
    "RICHMOND": 5,
    "ST PAUL": 5,
    "HUDSON OAKS": 5,
    "POWELL": 5,
    "LAMPASAS": 5,
    "SPRING BRANCH": 5,
    "TOOL": 5,
    "SEALY": 5,
    "ITALLY": 5,
    "ALLAN": 5,
    "CARROLLTON DR": 4,
    "KENNDALE": 4,
    "TALCO": 4,
    "WICHITA": 4,
    "LAKE WORTH": 4,
    "CROSS ROADS": 4,
    "TEMPLE": 4,
    "MAGNOLIA": 4,
    "SUGAR LAND": 4,
    "DRIFTWOOD": 4,
    "MUENSTAR": 4,
    "WESTON": 4,
    "FORESTBURG": 4,
    "MORGAN": 4,
    "WICHITA FALLAS": 4,
    "CELESTE": 4,
    "NORTH RICHLAND MILLS": 4,
    "LONE OAK": 4,
    "FORENY": 4,
    "COLLEVILLE": 4,
    "ROWLETE": 4,
    "CARROLLTION": 4,
    "GRAND PRIAIRE": 4,
    "WALLER": 4,
    "RAINBOW": 4,
    "KILGORE": 4,
    "AMARILLO": 4,
    "FAIRFIELD": 3,
    "BALCH SPRING": 3,
    "PEARLAND": 3,
    "COOPER": 3,
    "COPPER CANYON": 3,
    "FTWORTH": 3,
    "WHITE OAK": 3,
    "BRYAN": 3,
    "TIOGA": 3,
    "LIBERTY": 3,
    "ALVORDO": 3,
    "BLANCO": 3,
    "COLLINSVILLE": 3,
    "HALTON": 3,
    "DALLA": 3,
    "HEMPHILL": 3,
    "NRH": 3,
    "LANDCASTER": 3,
    "GRANDURY": 3,
    "CUERO": 3,
    "FLOWERMOUND": 3,
    "RICHLAND": 3,
    "MALAKOFF": 3,
    "CRESSON": 3,
    "CIBOLO": 3,
    "CARROLTTON": 3,
    "MCALLEN": 3,
    "WAXAHACIE": 3,
    "WHITE WRIGHT": 3,
    "STAGECOACH": 3,
    "HARKER HEIGHTS": 3,
    "SECHSE": 3,
    "NEW BRAUNFELS": 3,
    "PLAMO": 3,
    "MT PLEASANT": 3,
    "FRUITVALE": 3,
    "QUINTILAN": 2,
    "NEDERLAND": 2,
    "LOCKHART": 2,
    "STEHPENVILLE": 2,
    "CLUTE": 2,
    "RED  OAK": 2,
    "ALVIN": 2,
    "BUNHAM": 2,
    "DALLAS TX": 2,
    "GRAND PRIARIE": 2,
    "CROWELY": 2,
    "LEESBURG": 2,
    "HIGHLAND PARK": 2,
    "WHITEHOUSE": 2,
    "LARUE": 2,
    "RICAHRDSON": 2,
    "PASADENA": 2,
    "MILFORD": 2,
    "QUITMAN": 2,
    "SCURY": 2,
    "THRALL": 2,
    "ROWLETTE": 2,
    "LEXINGTON": 2,
    "ARLINGOTN": 2,
    "HORSESHOE BAY": 2,
    "SPLENDORA": 2,
    "LINDALE": 2,
    "WALNUT SPRINGS": 2,
    "LUFKIN": 2,
    "GRAND": 2,
    "SIGNAW": 2,
    "MADISONVILLE": 2,
    "CORPUS CHRISTI": 2,
    "DELEON": 2,
    "DALLLAS": 2,
    "MOUNT PLEASANT": 2,
    "AZELE": 2,
    "KEMAH": 2,
    "MESUITE": 2,
    "JACKSBORO": 2,
    "RIO VISTA": 2,
    "DAWSON": 2,
    "CHINA SPRING": 2,
    "CAMPBELL": 2,
    "TOM BEAN": 2,
    "WHITESORO": 2,
    "ROSHARON": 2,
    "MINERAL WELLS": 2,
    "AURORA": 2,
    "DRIPPING SPRINGS": 2,
    "DECATER": 2,
    "EL PASO": 2,
    "POOLVILLE": 2,
    "GELNN HEIGHTS": 2,
    "PALESTINE": 2,
    "LETTLE ELM": 2,
    "RICHADSON": 2,
    "HORIZON": 2,
    "ROGERS": 1,
    "ADDION": 1,
    "WIMBERLEY": 1,
    "ROWELTT": 1,
    "CASTROVILLE": 1,
    "BEAUMONT": 1,
    "LA FERIA": 1,
    "DEVIEN": 1,
    "BLUE MOUND": 1,
    "MANSFEILD": 1,
    "LAVOH": 1,
    "GRAPERVINE": 1,
    "BELLAIRE": 1,
    "WAXHACHIE": 1,
    "EDGECLIFF VILLAGE": 1,
    "WESTWORTH VILLAGE": 1,
    "WATANGA": 1,
    "SULLIVAN CITY": 1,
    "COLLEGE STATION": 1,
    "CRESTRIDGE RD": 1,
    "WAX": 1,
    "HARLETON": 1,
    "BROWNWOOD": 1,
    "ESCONDIDO": 1,
    "MANSIFELD": 1,
    "DALLASQ": 1,
    "BIG SPRING": 1,
    "SACHES": 1,
    "DENNIS": 1,
    "KOPPERL": 1,
    "ANDREWS": 1,
    "HUTTO": 1,
    "CORNITH": 1,
    "LORENA": 1,
    "RICHARDOSN": 1,
    "SACNSE": 1,
    "HEXT": 1,
    "NORTHRICHLAND HILLS": 1,
    "LARON": 1,
    "BROOKSHIRE": 1,
    "LEDBETTER": 1,
    "WATAUGE": 1,
    "FLINT": 1,
    "FARMERS BRNACH": 1,
    "SAINT JO": 1,
    "DLLAS": 1,
    "DALWORT GARDENS": 1,
    "MAUD": 1,
    "CEDARHILL": 1,
    "FORRESTON": 1,
    "KERRVILE": 1,
    "LINDSAY": 1,
    "N RICHLANDHILLS": 1,
    "CAYCE": 1,
    "SHADY SHORES": 1,
    "SOUTH SALT LAKE": 1,
    "ANGLETON": 1,
    "LUCUS": 1,
    "ROSENBERG": 1,
    "EAST HUMBLE": 1,
    "CEDER HILL": 1,
    "COAHOMA": 1,
    "LADONIA": 1,
    "HLLSBORO": 1,
    "PHARR": 1,
    "HARLINGEN": 1,
    "NORTH RICHLAND HILL": 1,
    "ARLIGNTON": 1,
    "COVINGTON": 1,
    "WHITSBORO": 1,
    "ROCKDALE": 1,
    "SASCHSE": 1,
    "KERENS": 1,
    "ROTTSBORO": 1,
    "FREDERICKSBURG": 1,
    "NAVASOTA": 1,
    "SAN MARCOS": 1,
    "WAXAHACHE": 1,
    "NOCONA": 1,
    "POETRY": 1,
    "CAROLLTON": 1,
    "DESTO": 1,
    "CARROLL": 1,
    "KYLE": 1,
    "LEWISILLE": 1,
    "SACHS": 1,
    "MONTGOMERY": 1,
    "WINNSBORO": 1,
    "CARROLLOTN": 1,
    "GRAPE VINE": 1,
    "WHITNEY": 1,
    "ALAMO": 1,
    "BRASHEAR": 1,
    "ANNE": 1,
    "BRYSON": 1,
    "SAN ANGELO": 1,
    "HALLSVILLE": 1,
    "BOERNE": 1,
    "OKLAHOMA CITY": 1,
    "SASCHE": 1,
    "POTOMAC": 1,
    "W INONA": 1,
    "ROANKE": 1,
    "KENDALE": 1,
    "CHICO": 1,
    "NEW CANEY": 1,
    "KENNARD": 1,
    "SEAGORVILLE": 1,
    "EUELESS": 1,
    "LA PORTE": 1,
    "CANYON LAKE": 1,
    "DUCANVILLE": 1,
    "SEAGOVALLE RD": 1,
    "GILMER": 1,
    "KILLEN": 1,
    "WEST": 1,
    "RENO": 1,
    "ALBA": 1,
    "FLOWER": 1,
    "BLOOMING GROVE": 1,
    "CARRILLTON": 1,
    "BIG SANDY": 1,
    "EASTLAND": 1,
    "DETROIT": 1,
    "NORTH COMBINE": 1,
    "HENDERSON": 1,
    "FTW": 1,
    "ELM MOTT": 1,
    "BROCK": 1,
    "BASTROP": 1,
    "SAN AUGUSTINE": 1,
    "FRANKSTON": 1,
    "TEMPE": 1,
    "MCGREGOR": 1,
    "BUDA": 1,
    "ORE CITY": 1
  },
  "feature_cols": [
    "Area",
    "issue_year",
    "issue_month",
    "issue_quarter",
    "days_since_epoch",
    "issue_day_of_week",
    "is_q4",
    "contractor_permit_count",
    "is_repeat_contractor",
    "contractor_city_freq",
    "permit_category_Backflow",
    "permit_category_Barricade",
    "permit_category_Building",
    "permit_category_Customer Service",
    "permit_category_Demolition Permit Commercial",
    "permit_category_Demolition Permit SFD/Duplex",
    "permit_category_Electrical",
    "permit_category_Electrical Sign Alteration",
    "permit_category_Electrical Sign New Construction",
    "permit_category_Electrical Sign Reconstruction",
    "permit_category_Electrical Sign Renovation",
    "permit_category_Elevator",
    "permit_category_Excavation",
    "permit_category_Fence",
    "permit_category_Fire Alarm",
    "permit_category_Fire Sprinkler (Major Work)",
    "permit_category_Fire Sprinkler (Minor Work)",
    "permit_category_Flammable Liquid",
    "permit_category_Grading and Paving",
    "permit_category_Lawn Sprinkler",
    "permit_category_Liquor License",
    "permit_category_Mechanical",
    "permit_category_Mechanical Refrigeration",
    "permit_category_Medical Gas",
    "permit_category_Paving (Sidewalk, Drive Approaches)",
    "permit_category_Plumbing",
    "permit_category_Security System",
    "permit_category_Sign Alteration",
    "permit_category_Sign New Construction",
    "permit_category_Sign Reconstruction",
    "permit_category_Sign Renovation",
    "permit_category_Special Purpose Sign New Construction",
    "permit_category_Supergraphics Alteration",
    "permit_category_Supergraphics New Construction",
    "permit_category_Swimming Pool",
    "permit_category_Tent",
    "permit_category_Tree Removal",
    "sub_category_Commercial",
    "sub_category_General",
    "sub_category_Multi Family",
    "sub_category_Single Family",
    "work_type_Addition",
    "work_type_Alteration",
    "work_type_Finish Out",
    "work_type_New Construction",
    "work_type_Other",
    "work_type_Reconstruction",
    "work_type_Renovation",
    "land_use_freq",
    "zip_target_encoded",
    "permit_code_freq",
    "area_value_ratio",
    "log_area"
  ],
  "feature_cols_reg": [
    "Area",
    "issue_year",
    "issue_month",
    "issue_quarter",
    "days_since_epoch",
    "issue_day_of_week",
    "is_q4",
    "contractor_permit_count",
    "is_repeat_contractor",
    "contractor_city_freq",
    "permit_category_Backflow",
    "permit_category_Barricade",
    "permit_category_Building",
    "permit_category_Customer Service",
    "permit_category_Demolition Permit Commercial",
    "permit_category_Demolition Permit SFD/Duplex",
    "permit_category_Electrical",
    "permit_category_Electrical Sign Alteration",
    "permit_category_Electrical Sign New Construction",
    "permit_category_Electrical Sign Reconstruction",
    "permit_category_Electrical Sign Renovation",
    "permit_category_Elevator",
    "permit_category_Excavation",
    "permit_category_Fence",
    "permit_category_Fire Alarm",
    "permit_category_Fire Sprinkler (Major Work)",
    "permit_category_Fire Sprinkler (Minor Work)",
    "permit_category_Flammable Liquid",
    "permit_category_Grading and Paving",
    "permit_category_Lawn Sprinkler",
    "permit_category_Liquor License",
    "permit_category_Mechanical",
    "permit_category_Mechanical Refrigeration",
    "permit_category_Medical Gas",
    "permit_category_Paving (Sidewalk, Drive Approaches)",
    "permit_category_Plumbing",
    "permit_category_Security System",
    "permit_category_Sign Alteration",
    "permit_category_Sign New Construction",
    "permit_category_Sign Reconstruction",
    "permit_category_Sign Renovation",
    "permit_category_Special Purpose Sign New Construction",
    "permit_category_Supergraphics Alteration",
    "permit_category_Supergraphics New Construction",
    "permit_category_Swimming Pool",
    "permit_category_Tent",
    "permit_category_Tree Removal",
    "sub_category_Commercial",
    "sub_category_General",
    "sub_category_Multi Family",
    "sub_category_Single Family",
    "work_type_Addition",
    "work_type_Alteration",
    "work_type_Finish Out",
    "work_type_New Construction",
    "work_type_Other",
    "work_type_Reconstruction",
    "work_type_Renovation",
    "land_use_freq",
    "zip_target_encoded",
    "permit_code_freq",
    "log_area"
  ],
  "ohe_permit_cats": [
    "permit_category_Backflow",
    "permit_category_Barricade",
    "permit_category_Building",
    "permit_category_Customer Service",
    "permit_category_Demolition Permit Commercial",
    "permit_category_Demolition Permit SFD/Duplex",
    "permit_category_Electrical",
    "permit_category_Electrical Sign Alteration",
    "permit_category_Electrical Sign New Construction",
    "permit_category_Electrical Sign Reconstruction",
    "permit_category_Electrical Sign Renovation",
    "permit_category_Elevator",
    "permit_category_Excavation",
    "permit_category_Fence",
    "permit_category_Fire Alarm",
    "permit_category_Fire Sprinkler (Major Work)",
    "permit_category_Fire Sprinkler (Minor Work)",
    "permit_category_Flammable Liquid",
    "permit_category_Grading and Paving",
    "permit_category_Lawn Sprinkler",
    "permit_category_Liquor License",
    "permit_category_Mechanical",
    "permit_category_Mechanical Refrigeration",
    "permit_category_Medical Gas",
    "permit_category_Paving (Sidewalk, Drive Approaches)",
    "permit_category_Plumbing",
    "permit_category_Security System",
    "permit_category_Sign Alteration",
    "permit_category_Sign New Construction",
    "permit_category_Sign Reconstruction",
    "permit_category_Sign Renovation",
    "permit_category_Special Purpose Sign New Construction",
    "permit_category_Supergraphics Alteration",
    "permit_category_Supergraphics New Construction",
    "permit_category_Swimming Pool",
    "permit_category_Tent",
    "permit_category_Tree Removal"
  ],
  "ohe_sub_cats": [
    "sub_category_Commercial",
    "sub_category_General",
    "sub_category_Multi Family",
    "sub_category_Single Family"
  ],
  "ohe_work_types": [
    "work_type_Addition",
    "work_type_Alteration",
    "work_type_Finish Out",
    "work_type_New Construction",
    "work_type_Other",
    "work_type_Reconstruction",
    "work_type_Renovation"
  ],
  "median_area": 191.0,
  "median_contractor_count": 51.0
}